voximplant/__init__.py
voximplant/apiclient/__init__.py
voximplant/apiclient/client.py
voximplant_apiclient-2.5.0.dist-info/licenses/LICENSE
voximplant_apiclient-2.5.0.dist-info/licenses/NOTICE
voximplant_apiclient-2.5.0.dist-info/METADATA
voximplant_apiclient-2.5.0.dist-info/WHEEL
voximplant_apiclient-2.5.0.dist-info/top_level.txt
voximplant_apiclient-2.5.0.dist-info/RECORD
