Metadata-Version: 2.4
Name: voximplant-apiclient
Version: 2.5.0
Summary: Voximplant API client library
Home-page: https://voximplant.com/
Author: Voximplant
Author-email: support@voximplant.com
Classifier: Programming Language :: Python
Classifier: License :: OSI Approved :: Apache Software License
Classifier: Operating System :: OS Independent
License-File: LICENSE
License-File: NOTICE
Requires-Dist: requests
Requires-Dist: pytz
Requires-Dist: pyjwt
Requires-Dist: cryptography
Dynamic: author
Dynamic: author-email
Dynamic: classifier
Dynamic: description
Dynamic: home-page
Dynamic: license-file
Dynamic: requires-dist
Dynamic: summary
